textsnippets/__init__.py
textsnippets/cli.py
textsnippets/core.py
textsnippets/py.typed
textsnippets-0.1.2.dist-info/METADATA
textsnippets-0.1.2.dist-info/WHEEL
textsnippets-0.1.2.dist-info/entry_points.txt
textsnippets-0.1.2.dist-info/top_level.txt
textsnippets-0.1.2.dist-info/RECORD
