Metadata-Version: 2.1
Name: textsnippets
Version: 0.1.2
Summary: A library for extracting and preparing code and text snippets from various file types, primarily intended for consumption by Large Language Models (LLMs).
Requires-Python: >=3.8
